CHANGES.rst
LICENSE
README.rst
requirements.txt
setup.py
stdeb.cfg
test_settings.py
doc/auth.rst
doc/conf.py
doc/index.rst
doc/localprofile.rst
doc/readme_from_docstring.py
doc/requirements.txt
doc/settings.rst
doc/views.rst
doc/_theme/nature/theme.conf
doc/_theme/nature/static/nature.css_t
doc/_theme/nature/static/pygments.css
doc/exts/document_init_methods.py
doc/exts/resolve_default_interpreted_role.py
doc/exts/set_up_django.py
typepadapp/__init__.py
typepadapp/admin.py
typepadapp/auth.py
typepadapp/cached_templates.py
typepadapp/caching.py
typepadapp/context_processors.py
typepadapp/decorators.py
typepadapp/forms.py
typepadapp/settings.py
typepadapp/signals.py
typepadapp/urls.py
typepadapp/conf/app_template/__init__.py
typepadapp/conf/app_template/models.py
typepadapp/conf/app_template/urls.py
typepadapp/conf/app_template/views.py
typepadapp/conf/app_template/static/theme/style.css
typepadapp/conf/app_template/templates/motion/.gitignore
typepadapp/conf/locale/en/LC_MESSAGES/django.po
typepadapp/conf/locale/fr/LC_MESSAGES/django.po
typepadapp/conf/project_template/__init__.py
typepadapp/conf/project_template/app.wsgi
typepadapp/conf/project_template/local_settings.py
typepadapp/conf/project_template/manage.py
typepadapp/conf/project_template/settings.py
typepadapp/conf/project_template/urls.py
typepadapp/locale/fr/LC_MESSAGES/django.mo
typepadapp/management/__init__.py
typepadapp/management/base.py
typepadapp/management/commands/__init__.py
typepadapp/management/commands/refreshwsgi.py
typepadapp/management/commands/tpappcreate.py
typepadapp/management/commands/tpsubcreate.py
typepadapp/management/commands/tpsubdelete.py
typepadapp/management/commands/tpsubinfo.py
typepadapp/management/commands/tpsubupdate.py
typepadapp/management/commands/typepadproject.py
typepadapp/middleware/__init__.py
typepadapp/middleware/config.py
typepadapp/middleware/debug.py
typepadapp/models/__init__.py
typepadapp/models/assets.py
typepadapp/models/auth.py
typepadapp/models/db.py
