Metadata-Version: 1.1
Name: typepadapp
Version: 1.2.1
Summary: A helper Django app for making TypePad applications
Home-page: http://github.com/sixapart/typepadapp
Author: Six Apart
Author-email: python@sixapart.com
License: UNKNOWN
Platform: UNKNOWN
Classifier: Development Status :: 4 - Beta
Classifier: Environment :: Console
Classifier: Environment :: Web Environment
Classifier: Framework :: Django
Classifier: Intended Audience :: Developers
Classifier: License :: OSI Approved :: BSD License
Classifier: Operating System :: MacOS :: MacOS X
Classifier: Operating System :: POSIX
Classifier: Programming Language :: Python
Classifier: Topic :: Internet :: WWW/HTTP
Requires: Django(>=1.1.1)
Requires: typepad(==2.0)
Requires: FeedParser
Requires: iso8601
Provides: typepadapp
